debussy_airflow
