Metadata-Version: 2.1
Name: debussy-airflow
Version: 0.0.5
Home-page: https://github.com/DotzInc/debussy_airflow
Author: Lawrence Fernandes
Author-email: github@lawrencestfs.com
License: Apache-2.0
Keywords: Debussy Framework,debussy_concert,airflow provider
Platform: any
Classifier: Operating System :: OS Independent
Classifier: License :: OSI Approved :: MIT License
Classifier: Topic :: Utilities
Classifier: Intended Audience :: Developers
Classifier: Topic :: Software Development :: Libraries :: Python Modules
Classifier: Programming Language :: Python :: 3.6
Classifier: Programming Language :: Python :: 3.7
Classifier: Programming Language :: Python :: 3.8
Classifier: Programming Language :: Python :: 3.9
Classifier: Programming Language :: Python :: 3.10
Requires-Python: >=3.6
License-File: LICENSE
